[
    {
        "id": 0,
        "nome": "Amendoin",
        "imagem": "card-1.jpg",
        "regiao": "Recife Pe",
        "especie": "Cachorro",
        "porte": "Medio",
        "sexo": "Maculino",
        "raca": "Vira-lata",
        "idade": 5,
        "vacinas": "muitas",
        "tratamento-pulgas": "sim",
        "castracao": "sim",
        "temperamento": "Dócil, se Acostumando com A vida ainda",
        "observacoes": "Não come ração"
    },

    {
        "id": 1,
        "nome": "Lindinha",
        "imagem": "card-2.png",
        "regiao": "Paulista Pe",
        "especie": "Cachorro",
        "porte": "Medio",
        "sexo": "Feminino",
        "raca": "Egipcia",
        "idade": 5,
        "vacinas": "muitas",
        "tratamento-pulgas": "sim",
        "castracao": "sim",
        "temperamento": "Dócil, se Acostumando com A vida ainda",
        "observacoes": "Não come ração"
    }, 

    {
        "id": 3,
        "nome": "Stuart Lirou",
        "imagem": "Stuart.jpg",
        "regiao": "Olinda",
        "especie": "Hamster",
        "porte": "Pequeno",
        "sexo": "Maculino",
        "raca": "Laranja",
        "idade": 1,
        "vacinas": "Muitas",
        "tratamento-pulgas": "não",
        "castracao": "Não",
        "temperamento": "Agitado",
        "observacoes": "Rapido como foguete"
    },

    {
        "id": 4,
        "nome": "Frajola",
        "imagem": "Frajolinha.jpg",
        "regiao": "Boa Viagem",
        "especie": "Gato",
        "porte": "Pequeno/medio",
        "sexo": "Maculino",
        "raca": "Branco e preto",
        "idade": 2 ,
        "vacinas": "muitas",
        "tratamento-pulgas": "sim",
        "castracao": "sim",
        "temperamento": "Dócil, Arisco com estranhos",
        "observacoes": "So Come Ração Premium"
    },

    {
        "id": 5,
        "nome": "Perna Curta",
        "imagem": "Perna.jpg",
        "regiao": "Ibura",
        "especie": "Coelho",
        "sexo": "Maculino",
        "porte": "Pequeno",
        "raca": "Cinza",
        "idade": 2 ,
        "vacinas": "muitas",
        "tratamento-pulgas": "sim",
        "castracao": "Não",
        "temperamento": "Agitado, Carente",
        "observacoes": "Coelho veloz"
    },

    {
        "id": 6,
        "nome": "Bom Bom",
        "imagem": "marrom.jpg",
        "regiao": "Casa Amarela",
        "especie": "Cachorro",
        "sexo": "Maculino",
        "porte": "Medio/grande",
        "raca": "Labrador",
        "idade": 1 ,
        "vacinas": "Antirabica",
        "tratamento-pulgas": "Sim",
        "castracao": "sim",
        "temperamento": "Dócil",
        "observacoes": "Carinhoso, Mas treloso, so Come Ração Premium"
    },
    

    {
        "id": 7,
        "nome": "Laranjinha",
        "imagem": "Laranjinha.jpg",
        "regiao": "Paulista Pe",
        "especie": "Gato",
        "sexo": "Maculino",
        "porte": "Pequeno/Medio",
        "raca": "vira-lata",
        "idade": 3 ,
        "vacinas": "muitas",
        "tratamento-pulgas": "sim",
        "castracao": "Não",
        "temperamento": "Raivoso",
        "observacoes": "Não come ração"
    },

    {
        "id": 8,
        "nome": "Bento",
        "imagem": "Gato-cara-cu.jpg",
        "regiao": "San Martin Pe",
        "especie": "Gato",
        "sexo": "Masculino",
        "porte": "Pequeno/Medio",
        "raca": "Siames",
        "idade": 6 ,
        "vacinas": "Antirabica",
        "tratamento-pulgas": "sim",
        "castracao": "sim",
        "temperamento": "Medrosa",
        "observacoes": "Fresco com comida, so gosta Da Ração Premium"
    },

    {
        "id": 9,
        "nome": "Francisco",
        "imagem": "Gato-do-mato.jpg",
        "regiao": "São Lourenço da Mata PE",
        "especie": "Gata",
        "sexo": "Maculino",
        "porte": "Medio",
        "raca": "vira-lata",
        "idade": 2 ,
        "vacinas": "Antirabica",
        "tratamento-pulgas": "sim",
        "castracao": "Não",
        "temperamento": "Arisco e um Pouco raivoso",
        "observacoes": "Encontrei no Mato, Achei que era um gato normal, mas comecou a comer rato, timbu, quase mata meu cachorro, ai quis colocar para adoção porque hoje pode ser o cachorro, ammanha pode ser eu..."
    },

    {
        "id": 10,
        "nome": "Banguela",
        "imagem": "gato-preto.jpg",
        "regiao": "Jaboatão dos Guararapes",
        "especie": "Gato",
        "sexo": "Maculino",
        "porte": "Pequeno",
        "raca": "Preto",
        "idade": 2 ,
        "vacinas": "Todas",
        "tratamento-pulgas": "sim",
        "castracao": "sim",
        "temperamento": "Dócil, Brincalhão",
        "observacoes": "Cuidado com as Sandalias, Provavelmente Vão ser Alvos do Banguela"
    },

    {
        "id": 11,
        "nome": "Flocos",
        "imagem": "Dalmata.jpg",
        "regiao": "Piedade",
        "especie": "Cachorro",
        "sexo": "Maculino",
        "porte": "Medio/Grande",
        "raca": "Dalmata",
        "idade": 2 ,
        "vacinas": "muitas",
        "tratamento-pulgas": "sim",
        "castracao": "sim",
        "temperamento": "Dócil, se Acostumando com A vida ainda",
        "observacoes": "So estou Fazendo essa doação poque vou me mudar para um apartamento e não posso leva-lo"
    },

    {
        "id": 12,
        "nome": "Princesa",
        "imagem": "Princesa.jpg",
        "regiao": "Encruzilhada PE",
        "especie": "Cachorro",
        "sexo": "Feminino",
        "porte": "Medio/Grande",
        "raca": "Pitbull",
        "idade": 3,
        "vacinas": "muitas",
        "tratamento-pulgas": "sim",
        "castracao": "Não",
        "temperamento": "Dócil, Não morde, carinhosa",
        "observacoes": "So Come Ração Premium, Se Não der a Ração, Voce Vira..."
    }

]